order_management.py
user_management.py
Online_magazin52-0.1.0.dist-info/METADATA
Online_magazin52-0.1.0.dist-info/WHEEL
Online_magazin52-0.1.0.dist-info/top_level.txt
Online_magazin52-0.1.0.dist-info/RECORD
